jaikit/__init__.py
jaikit/config.py
jaikit/character/__init__.py
jaikit/character/cjk_detail.py
jaikit/character/eng_chn.py
jaikit/character/unicode.py
jaikit/data/__init__.py
jaikit/data/lexicon.txt
jaikit/data/unicode_info.pkl
jaikit/datascience/__init__.py
jaikit/datascience/calculate.py
jaikit/datascience/one_hot.py
jaikit/datascience/plot.py
jaikit/datastructure/__init__.py
jaikit/datastructure/flat_to_tree.py
jaikit/datastructure/max_match.py
jaikit/datastructure/trie.py
jaikit/nlp/__init__.py
jaikit/nlp/word_segment.py
jaikit-0.0.8.dist-info/METADATA
jaikit-0.0.8.dist-info/WHEEL
jaikit-0.0.8.dist-info/top_level.txt
jaikit-0.0.8.dist-info/RECORD
